LICENSE.txt
README.md
setup.cfg
setup.py
xarrayfrac/__init__.py
xarrayfrac/frac_backend.py
xarrayfrac.egg-info/PKG-INFO
xarrayfrac.egg-info/SOURCES.txt
xarrayfrac.egg-info/dependency_links.txt
xarrayfrac.egg-info/entry_points.txt
xarrayfrac.egg-info/requires.txt
xarrayfrac.egg-info/top_level.txt