Metadata-Version: 2.1
Name: xarrayfrac
Version: 0.0.6
Summary: mandelbrot dynamically generated xarray backend
Home-page: https://github.com/benjaminleighton/xarrayfrac
Author: Ben Leighton
Author-email: benplei@gmail.com
License: UNKNOWN
Platform: UNKNOWN
License-File: LICENSE.txt
